Metadata-Version: 2.1
Name: spacedb
Version: 1.0.0
Summary: simple json database for test projects
Home-page: https://github.com/fxckfxtxre/SpaceDB
Author: cxldxice
License: UNKNOWN
Keywords: database,db,json
Platform: UNKNOWN
